{
  "bundle": "tilly-engineer-skills-0.3.135.zip",
  "created_at": "2026-05-26T15:27:32-03:00",
  "manifest": "tes-bundle-manifest.json",
  "metadata": {
    "created_at": "2026-05-26T15:27:32-03:00",
    "schema": "tes-bundle-metadata@1",
    "source_branch": "main",
    "source_commit": "3f2cfddaf6170a0be7d5e28c63a1deb9b9911280",
    "source_ref": "HEAD",
    "source_repository": "https://github.com/murillodutt/tilly-engineer-skills.git",
    "source_tree_state": "dirty",
    "version": "0.3.135"
  },
  "schema": "tes-public-bundle-index@1",
  "sha256": "4358d39fd6c5afdf9e92413f0d6f42359e88b0bca5ae14ac48d407136eaadad2",
  "sha256_file": "tilly-engineer-skills-0.3.135.zip.sha256",
  "source_commit": "3f2cfddaf6170a0be7d5e28c63a1deb9b9911280",
  "source_repository": "https://github.com/murillodutt/tilly-engineer-skills.git",
  "stage_dir": ".tes/setup/0.3.135",
  "urls": {
    "bundle": "https://murillodutt.github.io/tilly-engineer-skills/dist/0.3.135/tilly-engineer-skills-0.3.135.zip",
    "sha256": "https://murillodutt.github.io/tilly-engineer-skills/dist/0.3.135/tilly-engineer-skills-0.3.135.zip.sha256"
  },
  "version": "0.3.135"
}
